{"key_id":"10876","key_title":"Key to the species of Machaerina","key_author":"","modified_from_source":false,"UID":"010583","description":"","rank":null,"taxonomic_scope":{"item_id":"5966","item_name":"Machaerina","url":"https:\/\/vicflora.rbg.vic.gov.au\/flora\/taxon\/5ae20b4c-7759-46c1-8325-b2bb4ada6756"},"geographic_scope":"Victoria","notes":"","source_id":null,"created_by_id":"45","timestamp_created":"2020-06-29 16:41:49","modified_by_id":"1","timestamp_modified":"2020-06-29 16:43:54","project":{"project_id":"10","project_name":"Flora of Victoria","project_icon":"https:\/\/keybase.rbg.vic.gov.au\/images\/projecticons\/epacris.png"},"breadcrumbs":[{"key_id":"1903","key_title":"Key to the main groups of plants in Victoria"},{"key_id":"1906","key_title":"Key to the families of Monocotyledons"},{"key_id":"1986","key_title":"Key to the genera of Cyperaceae"}],"key_name":"Machaerina","source":{"author":null,"publication_year":null,"title":null,"in_author":null,"in_title":null,"edition":null,"journal":null,"series":null,"volume":null,"part":null,"publisher":null,"place_of_publication":null,"page":null,"is_modified":null,"url":null,"citation":false},"items":[{"item_id":"73358","item_name":"Machaerina acuta","url":"https:\/\/vicflora.rbg.vic.gov.au\/flora\/taxon\/c51229d3-b2ce-4e2e-afea-fc929aa3c112","to_key":null},{"item_id":"73363","item_name":"Machaerina arthrophylla","url":"https:\/\/vicflora.rbg.vic.gov.au\/flora\/taxon\/7ae85abb-4e9b-497e-a6c8-521f73282bd8","to_key":null},{"item_id":"73361","item_name":"Machaerina articulata","url":"https:\/\/vicflora.rbg.vic.gov.au\/flora\/taxon\/cdb074ec-20bd-4a97-84f7-46e6e9e984e2","to_key":null},{"item_id":"73362","item_name":"Machaerina gunnii","url":"https:\/\/vicflora.rbg.vic.gov.au\/flora\/taxon\/5cb3f4c0-32bc-44be-8961-53919a42a1e5","to_key":null},{"item_id":"73355","item_name":"Machaerina juncea","url":"https:\/\/vicflora.rbg.vic.gov.au\/flora\/taxon\/dca31da8-8410-4091-84b5-4fcdf604b057","to_key":null},{"item_id":"73359","item_name":"Machaerina laxa","url":"https:\/\/vicflora.rbg.vic.gov.au\/flora\/taxon\/b49a45ea-0fcd-4f39-b95b-e78ccd2f0cbc","to_key":null},{"item_id":"73357","item_name":"Machaerina planifolia","url":"https:\/\/vicflora.rbg.vic.gov.au\/flora\/taxon\/6b0c2e5d-f117-4211-a960-8ad980863d03","to_key":null},{"item_id":"73360","item_name":"Machaerina rubiginosa","url":"https:\/\/vicflora.rbg.vic.gov.au\/flora\/taxon\/22ba7c15-ca39-4915-8a0b-0d9f635a7180","to_key":null},{"item_id":"73356","item_name":"Machaerina tetragona","url":"https:\/\/vicflora.rbg.vic.gov.au\/flora\/taxon\/37458713-a901-4a12-9210-123171b1adec","to_key":null}],"first_step":{"root_node_id":"1103685"},"leads":[{"parent_id":"1103685","lead_id":"1103686","lead_text":"Leaf-blades flat or 4-angled in cross-section, or all reduced to flattened mucros on sheaths","item":null},{"parent_id":"1103685","lead_id":"1103703","lead_text":"Leaf-blades terete or oval in cross-section (rarely somewhat angular or flattened at apex)","item":null},{"parent_id":"1103686","lead_id":"1103687","lead_text":"All leaves reduced to flattened mucros; culms 1\u20133-noded","item":"73355"},{"parent_id":"1103686","lead_id":"1103689","lead_text":"Basal leaves well-developed (cauline leaves reduced if present); culms nodeless or 1-(rarely 2)-noded","item":null},{"parent_id":"1103689","lead_id":"1103690","lead_text":"Leaves square to rhomboid (occasionally narrowly so) in cross-section, faces concave or occasionally flat","item":"73356"},{"parent_id":"1103689","lead_id":"1103692","lead_text":"Leaves flattened (at least near apex in B. rubiginosa) or narrow-rhomboid, faces flat or convex","item":null},{"parent_id":"1103692","lead_id":"1103693","lead_text":"Leaves scabrous, with raised'midrib'even if otherwise flat","item":"73357"},{"parent_id":"1103692","lead_id":"1103695","lead_text":"Leaves smooth, without a raised 'midrib'","item":null},{"parent_id":"1103695","lead_id":"1103696","lead_text":"Spikelets 1-flowered; glumes 3 or 4; inflorescence 2\u20136 cm long (rarely to 14 cm), no more than 1 cm dia","item":"73358"},{"parent_id":"1103695","lead_id":"1103698","lead_text":"Spikelets 2\u20135-flowered; glumes 4 or 5; inflorescence usually 15\u201340 cm long (occasionally as short as 7 cm), 1\u20132.5 cm dia","item":null},{"parent_id":"1103698","lead_id":"1103699","lead_text":"Nut straw-coloured to red-brown; culms nodeless; leaves flat throughout; spikelets \u00b1 few, spread out on long branches","item":"73359"},{"parent_id":"1103698","lead_id":"1103701","lead_text":"Nut bright orange (paler red-brown when immature); culms 1\u20132-noded (rarely nodeless); leaves often terete near base; spikelets numerous, in dense discrete clusters","item":"73360"},{"parent_id":"1103703","lead_id":"1103704","lead_text":"Leaves hollow, perfectly transversely septate","item":"73361"},{"parent_id":"1103703","lead_id":"1103706","lead_text":"Leaves pith-filled, occasionally irregularly transversely septate","item":null},{"parent_id":"1103706","lead_id":"1103707","lead_text":"Spikelets few, not in dense clusters, 1-flowered; glumes 2\u20134 (mostly 3)","item":"73362"},{"parent_id":"1103706","lead_id":"1103709","lead_text":"Spikelets numerous, often clustered, 1\u20134-flowered; glumes 4\u20136","item":null},{"parent_id":"1103709","lead_id":"1103710","lead_text":"Nut straw-coloured to whitish, with acute apex, triquetrous, 2.0\u20132.5 mm long, 1.0\u20131.3 mm diam.; spikelets spaced \u00b1 evenly along branches; leaf-blades and involucral bracts terete and obviously transversely septate when dry","item":"73363"},{"parent_id":"1103709","lead_id":"1103712","lead_text":"Nut pale red-brown to bright orange at maturity, with obtuse apex, obscurely trigonous, 2.2\u20134.0 mm long, 1.2\u20132.0 mm diam.; spikelets usually in dense, discrete clusters on inflorescence branches; leaf-blades and involucral bracts flattened at least at apex, not appearing septate when dry","item":"73360"}]}