{"key_id":"12193","key_title":"Key to Leucobryaceae genera","key_author":"","modified_from_source":false,"UID":"011900","description":"","rank":null,"taxonomic_scope":{"item_id":"66747","item_name":"Leucobryaceae","url":"https:\/\/vicflora.rbg.vic.gov.au\/flora\/taxon\/1e3b56e2-26f5-4a27-a941-d9c2fcc424b6"},"geographic_scope":"Victoria","notes":"","source_id":null,"created_by_id":"51","timestamp_created":"2021-07-26 14:03:40","modified_by_id":"1","timestamp_modified":"2021-07-26 04:03:41","project":{"project_id":"10","project_name":"Flora of Victoria","project_icon":"https:\/\/keybase.rbg.vic.gov.au\/images\/projecticons\/epacris.png"},"breadcrumbs":[],"key_name":"Leucobryaceae","source":{"author":null,"publication_year":null,"title":null,"in_author":null,"in_title":null,"edition":null,"journal":null,"series":null,"volume":null,"part":null,"publisher":null,"place_of_publication":null,"page":null,"is_modified":null,"url":null,"citation":false},"items":[{"item_id":"25349","item_name":"Campylopus","url":"https:\/\/vicflora.rbg.vic.gov.au\/flora\/taxon\/d332a0f0-1ca4-4fa0-9a42-7f77e736941d","to_key":"12144"},{"item_id":"45941","item_name":"Leucobryum","url":"https:\/\/vicflora.rbg.vic.gov.au\/flora\/taxon\/e614f383-9018-4172-a1d3-0b1088bd5474","to_key":null}],"first_step":{"root_node_id":"1257909"},"leads":[{"parent_id":"1257909","lead_id":"1257910","lead_text":"Plants variously green to brown, not glaucous or whitish; lamina well developed, at least the more apical laminal cells chlorophyllose; costa well developed, broad but not occupying almost the entire leaf width at the base","item":"25349"},{"parent_id":"1257909","lead_id":"1257912","lead_text":"Plants glaucous or pale to whitish green; lamina forming a narrow border to the costa; laminal cells hyaline throughout the leaf; costa occupying almost the entire leaf width, consisting of a layer of narrow chlorophyllose cells sandwiched between layers of empty hyaline cells","item":"45941"}]}