{"key_id":"2386","key_title":"Key to the subspecies of Daviesia mimosoides","key_author":null,"modified_from_source":true,"UID":"002093","description":null,"rank":"subspecies","taxonomic_scope":{"item_id":"21880","item_name":"Daviesia mimosoides","url":"https:\/\/vicflora.rbg.vic.gov.au\/flora\/taxon\/5eec8436-9833-4c94-9d1e-fd7983677024"},"geographic_scope":"Victoria","notes":null,"source_id":"1881","created_by_id":"1","timestamp_created":"2013-08-06 00:00:00","modified_by_id":"1","timestamp_modified":"2013-08-05 19:29:40","project":{"project_id":"10","project_name":"Flora of Victoria","project_icon":"https:\/\/keybase.rbg.vic.gov.au\/images\/projecticons\/epacris.png"},"breadcrumbs":[{"key_id":"1903","key_title":"Key to the main groups of plants in Victoria"},{"key_id":"1907","key_title":"Key to the families of Dicotyledons"},{"key_id":"4442","key_title":"Key to the subfamilies of Fabaceae"},{"key_id":"2359","key_title":"Key to the genera of Fabaceae subfam. Faboideae"},{"key_id":"2385","key_title":"Key to the species of Daviesia"}],"key_name":"Daviesia mimosoides","source":{"author":"Jeanes, J.A.","publication_year":"1996","title":"Fabaceae","in_author":"Walsh, N.G.; Entwisle, T.J. (eds)","in_title":"Flora of Victoria. Vol. 3. Dicotyledons Winteraceae to Myrtaceae","edition":"","journal":"","series":null,"volume":"","part":"","publisher":"Inkata Press","place_of_publication":"Melbourne","page":"","is_modified":"1","url":"","citation":"Modified from: <b>Jeanes, J.A.<\/b> (1996). Fabaceae. In: Walsh, N.G.; Entwisle, T.J. (eds), <i>Flora of Victoria. Vol. 3. Dicotyledons Winteraceae to Myrtaceae<\/i>. Inkata Press,  Melbourne."},"items":[{"item_id":"2227","item_name":"Daviesia mimosoides subsp. acris","url":"https:\/\/vicflora.rbg.vic.gov.au\/flora\/taxon\/5a19a5a8-5e67-415c-a7e6-ac14518ca13a","to_key":null},{"item_id":"2226","item_name":"Daviesia mimosoides subsp. mimosoides","url":"https:\/\/vicflora.rbg.vic.gov.au\/flora\/taxon\/351a41cb-65ad-47fc-8ffb-63cd69d08c48","to_key":null}],"first_step":{"root_node_id":"235200"},"leads":[{"parent_id":"235200","lead_id":"235201","lead_text":"Phyllodes elliptic or obovate, slightly glaucous, base cuneate, margins obscurely minutely crenate","item":"2227"},{"parent_id":"235200","lead_id":"235203","lead_text":"Phyllodes linear, narrow-elliptic or narrow-obovate, dull green to glaucous, base tapered, margins not minutely crenate","item":"2226"}]}