{"key_id":"2497","key_title":"Key to the species of Melianthus","key_author":null,"modified_from_source":false,"UID":"002204","description":null,"rank":"species","taxonomic_scope":{"item_id":"8802","item_name":"Melianthus","url":"https:\/\/vicflora.rbg.vic.gov.au\/flora\/taxon\/52b90553-7a15-4657-91ef-a807fb1c07b3"},"geographic_scope":"Victoria","notes":null,"source_id":"2012","created_by_id":"1","timestamp_created":"2013-08-06 00:00:00","modified_by_id":"1","timestamp_modified":"2013-08-05 19:29:47","project":{"project_id":"10","project_name":"Flora of Victoria","project_icon":"https:\/\/keybase.rbg.vic.gov.au\/images\/projecticons\/epacris.png"},"breadcrumbs":[],"key_name":"Melianthus","source":{"author":"Jeanes, J.A.","publication_year":"1999","title":"Melianthaceae","in_author":"Walsh, N.G.; Entwisle, T.J. (eds)","in_title":"Flora of Victoria. Vol. 4. Cornaceae to Asteraceae","edition":null,"journal":null,"series":null,"volume":null,"part":null,"publisher":"Inkata Press","place_of_publication":"Melbourne","page":null,"is_modified":null,"url":null,"citation":"From: <b>Jeanes, J.A.<\/b> (1999). Melianthaceae. In: Walsh, N.G.; Entwisle, T.J. (eds), <i>Flora of Victoria. Vol. 4. Cornaceae to Asteraceae<\/i>. Inkata Press,  Melbourne."},"items":[{"item_id":"8804","item_name":"Melianthus comosus","url":"https:\/\/vicflora.rbg.vic.gov.au\/flora\/taxon\/8cc87369-63df-41d8-8d05-01c4c9ff8aa9","to_key":null},{"item_id":"8803","item_name":"Melianthus major","url":"https:\/\/vicflora.rbg.vic.gov.au\/flora\/taxon\/ba43443a-5b1a-4e1d-84f3-30db9905d061","to_key":null}],"first_step":{"root_node_id":"237496"},"leads":[{"parent_id":"237496","lead_id":"237497","lead_text":"Stipules free, subulate; leaflets densely tomentose below","item":"8804"},{"parent_id":"237496","lead_id":"237499","lead_text":"Stipules wholly united, lanceolate; leaflets glabrous below","item":"8803"}]}