{"key_id":"4402","key_title":"Key to the species of Galenia","key_author":null,"modified_from_source":false,"UID":"004109","description":"","rank":"species","taxonomic_scope":{"item_id":"4988","item_name":"Galenia","url":null},"geographic_scope":"Victoria","notes":"","source_id":"2492","created_by_id":"34","timestamp_created":"2015-03-23 12:02:54","modified_by_id":"34","timestamp_modified":"2015-03-23 12:02:54","project":{"project_id":"10","project_name":"Flora of Victoria","project_icon":"https:\/\/keybase.rbg.vic.gov.au\/images\/projecticons\/epacris.png"},"breadcrumbs":[],"key_name":"Galenia","source":{"author":"Messina, A.","publication_year":"","title":"","in_author":"","in_title":"","edition":"","journal":"","series":null,"volume":"","part":"","publisher":"","place_of_publication":"","page":"","is_modified":null,"url":"","citation":false},"items":[{"item_id":"9604","item_name":"Galenia pubescens","url":null,"to_key":null},{"item_id":"9605","item_name":"Galenia secunda","url":null,"to_key":null}],"first_step":{"root_node_id":"475323"},"leads":[{"parent_id":"475323","lead_id":"475324","lead_text":"Leaves and stems sparsely to moderately pilose, hairs closely appressed, less than 1 mm long","item":"9604"},{"parent_id":"475323","lead_id":"475326","lead_text":"Leaves and stems densely villous, hairs loosely appressed to spreading, more than 1 mm long","item":"9605"}]}