{"key_id":"6153","key_title":"Key to the forms of Haloragis acutangula","key_author":null,"modified_from_source":false,"UID":"005860","description":"","rank":"forma","taxonomic_scope":{"item_id":"5511","item_name":"Haloragis acutangula","url":"https:\/\/vicflora.rbg.vic.gov.au\/flora\/taxon\/cc57bf87-e3b0-4aed-84ad-82421765f43c"},"geographic_scope":"Victoria","notes":"","source_id":null,"created_by_id":"34","timestamp_created":"2016-05-31 17:04:41","modified_by_id":"34","timestamp_modified":"2016-05-31 17:04:41","project":{"project_id":"10","project_name":"Flora of Victoria","project_icon":"https:\/\/keybase.rbg.vic.gov.au\/images\/projecticons\/epacris.png"},"breadcrumbs":[{"key_id":"1903","key_title":"Key to the main groups of plants in Victoria"},{"key_id":"1907","key_title":"Key to the families of Dicotyledons"},{"key_id":"2414","key_title":"Key to the genera of Haloragaceae"},{"key_id":"2416","key_title":"Key to the species of Haloragis"}],"key_name":"Haloragis acutangula","source":{"author":null,"publication_year":null,"title":null,"in_author":null,"in_title":null,"edition":null,"journal":null,"series":null,"volume":null,"part":null,"publisher":null,"place_of_publication":null,"page":null,"is_modified":null,"url":null,"citation":false},"items":[{"item_id":"36555","item_name":"Haloragis acutangula f. acutangula","url":"https:\/\/vicflora.rbg.vic.gov.au\/flora\/taxon\/1b478333-6414-44e1-b289-233c56bd4cc5","to_key":null},{"item_id":"36556","item_name":"Haloragis acutangula f. tetraptera","url":"https:\/\/vicflora.rbg.vic.gov.au\/flora\/taxon\/03222344-6efb-4e5a-8651-5ba4cb0fcee4","to_key":null}],"first_step":{"root_node_id":"668444"},"leads":[{"parent_id":"668444","lead_id":"668445","lead_text":"Fruit distinctly winged, as wide as or wider than long","item":"36556"},{"parent_id":"668444","lead_id":"668447","lead_text":"Fruit 4-ribbed, longer than wide","item":"36555"}]}