{"key_id":"6162","key_title":"Key to the species of Sannantha","key_author":null,"modified_from_source":false,"UID":"005869","description":"","rank":"species","taxonomic_scope":{"item_id":"9906","item_name":"Sannantha","url":"https:\/\/vicflora.rbg.vic.gov.au\/flora\/taxon\/9d673bdf-a46f-4fa7-a0dc-bd16bbc47286"},"geographic_scope":"Victoria","notes":"","source_id":null,"created_by_id":"34","timestamp_created":"2016-06-20 14:44:03","modified_by_id":"34","timestamp_modified":"2016-06-20 14:45:09","project":{"project_id":"10","project_name":"Flora of Victoria","project_icon":"https:\/\/keybase.rbg.vic.gov.au\/images\/projecticons\/epacris.png"},"breadcrumbs":[{"key_id":"1903","key_title":"Key to the main groups of plants in Victoria"},{"key_id":"1907","key_title":"Key to the families of Dicotyledons"},{"key_id":"2434","key_title":"Key to the genera of Myrtaceae"}],"key_name":"Sannantha","source":{"author":null,"publication_year":null,"title":null,"in_author":null,"in_title":null,"edition":null,"journal":null,"series":null,"volume":null,"part":null,"publisher":null,"place_of_publication":null,"page":null,"is_modified":null,"url":null,"citation":false},"items":[{"item_id":"36931","item_name":"Sannantha crenulata","url":"https:\/\/vicflora.rbg.vic.gov.au\/flora\/taxon\/21ad9b31-feb8-4d69-a802-c7e5db09af73","to_key":null},{"item_id":"36932","item_name":"Sannantha pluriflora","url":"https:\/\/vicflora.rbg.vic.gov.au\/flora\/taxon\/886e5a84-5fc4-400d-8fde-3045a581cbad","to_key":null}],"first_step":{"root_node_id":"671707"},"leads":[{"parent_id":"671707","lead_id":"671708","lead_text":"Leaves ovate to orbicular, obtuse, margins minutely crenulate; flowers 2\u20133 per umbel","item":"36931"},{"parent_id":"671707","lead_id":"671710","lead_text":"Leaves lanceolate to elliptic, usually acute, margins entire; flowers 2\u20139 per umbel","item":"36932"}]}