{"key_id":"6196","key_title":"Key to the subspecies of Eucalyptus radiata","key_author":null,"modified_from_source":false,"UID":"005903","description":"","rank":"subspecies","taxonomic_scope":{"item_id":"19107","item_name":"Eucalyptus radiata","url":"https:\/\/vicflora.rbg.vic.gov.au\/flora\/taxon\/161c29e7-7b60-41d0-af4d-ac0e3dff3dee"},"geographic_scope":"Victoria","notes":"","source_id":null,"created_by_id":"34","timestamp_created":"2016-07-20 10:15:50","modified_by_id":"34","timestamp_modified":"2016-07-20 10:15:51","project":{"project_id":"10","project_name":"Flora of Victoria","project_icon":"https:\/\/keybase.rbg.vic.gov.au\/images\/projecticons\/epacris.png"},"breadcrumbs":[{"key_id":"1903","key_title":"Key to the main groups of plants in Victoria"},{"key_id":"1907","key_title":"Key to the families of Dicotyledons"},{"key_id":"2434","key_title":"Key to the genera of Myrtaceae"},{"key_id":"6607","key_title":"Key to the species of Eucalyptus"}],"key_name":"Eucalyptus radiata","source":{"author":null,"publication_year":null,"title":null,"in_author":null,"in_title":null,"edition":null,"journal":null,"series":null,"volume":null,"part":null,"publisher":null,"place_of_publication":null,"page":null,"is_modified":null,"url":null,"citation":false},"items":[{"item_id":"36448","item_name":"Eucalyptus radiata subsp. radiata","url":"https:\/\/vicflora.rbg.vic.gov.au\/flora\/taxon\/1e46e312-c0e4-4cc2-b8ca-c8fb9fe8cca3","to_key":null},{"item_id":"36449","item_name":"Eucalyptus radiata subsp. robertsonii","url":"https:\/\/vicflora.rbg.vic.gov.au\/flora\/taxon\/048cc090-cca3-4c65-acf1-1ec833caa147","to_key":null}],"first_step":{"root_node_id":"675271"},"leads":[{"parent_id":"675271","lead_id":"675272","lead_text":"Leaves grey-green; buds slightly to distinctly glaucous; operculum pointed","item":"36449"},{"parent_id":"675271","lead_id":"675274","lead_text":"Leaves green; buds not glaucous; operculum usually not pointed","item":"36448"}]}