{"key_id":"8862","key_title":"Key to the subspecies of Eucalyptus wimmerensis","key_author":"","modified_from_source":false,"UID":"008569","description":"","rank":null,"taxonomic_scope":{"item_id":"36465","item_name":"Eucalyptus wimmerensis","url":"https:\/\/vicflora.rbg.vic.gov.au\/flora\/taxon\/91cc5afa-bca3-413f-a2d2-949c5ae79652"},"geographic_scope":"Victoria","notes":"","source_id":"3641","created_by_id":"34","timestamp_created":"2018-10-02 17:30:55","modified_by_id":"1","timestamp_modified":"2018-10-02 16:37:28","project":{"project_id":"10","project_name":"Flora of Victoria","project_icon":"https:\/\/keybase.rbg.vic.gov.au\/images\/projecticons\/epacris.png"},"breadcrumbs":[{"key_id":"1903","key_title":"Key to the main groups of plants in Victoria"},{"key_id":"1907","key_title":"Key to the families of Dicotyledons"},{"key_id":"2434","key_title":"Key to the genera of Myrtaceae"},{"key_id":"6607","key_title":"Key to the species of Eucalyptus"}],"key_name":"Eucalyptus wimmerensis","source":{"author":"Rule, K.","publication_year":"2018","title":"Eucalyptus wimmerensis revisited and notes on the morphologies and taxonomies of five Victorian mallee-boxes","in_author":null,"in_title":null,"edition":null,"journal":"Muelleria","series":null,"volume":"37","part":null,"publisher":null,"place_of_publication":null,"page":"39-64","is_modified":null,"url":null,"citation":"From: <b>Rule, K.<\/b> (2018). Eucalyptus wimmerensis revisited and notes on the morphologies and taxonomies of five Victorian mallee-boxes. <i>Muelleria<\/i> <b>37<\/b>:39-64."},"items":[{"item_id":"63638","item_name":"Eucalyptus wimmerensis subsp. arapilensis","url":"https:\/\/vicflora.rbg.vic.gov.au\/flora\/taxon\/c137809c-2f48-491b-9cd8-4c9953c59fba","to_key":null},{"item_id":"63641","item_name":"Eucalyptus wimmerensis subsp. grata","url":"https:\/\/vicflora.rbg.vic.gov.au\/flora\/taxon\/d57c9a9b-1b00-4f0f-83fe-56d7b89f9671","to_key":null},{"item_id":"63640","item_name":"Eucalyptus wimmerensis subsp. pallida","url":"https:\/\/vicflora.rbg.vic.gov.au\/flora\/taxon\/560e9042-32f0-40b5-ad37-d086df583741","to_key":null},{"item_id":"63639","item_name":"Eucalyptus wimmerensis subsp. parviformis","url":"https:\/\/vicflora.rbg.vic.gov.au\/flora\/taxon\/7ede693a-406b-4e36-b168-4232c9b0679f","to_key":null},{"item_id":"63637","item_name":"Eucalyptus wimmerensis subsp. wimmerensis","url":"https:\/\/vicflora.rbg.vic.gov.au\/flora\/taxon\/a1e34a0f-0806-44a2-8ec4-32ee0f5e9f99","to_key":null}],"first_step":{"root_node_id":"983359"},"leads":[{"parent_id":"983359","lead_id":"983360","lead_text":"Adult leaves dull, blue-green to subglaucous","item":"63640"},{"parent_id":"983359","lead_id":"983362","lead_text":"Adult leaves sub-lustrous to lustrous, olive green, or green, sometimes with a bluish tinge","item":null},{"parent_id":"983362","lead_id":"983363","lead_text":"Bark smooth throughout","item":null},{"parent_id":"983362","lead_id":"983368","lead_text":"Box bark present on at least lower stem","item":null},{"parent_id":"983363","lead_id":"983364","lead_text":"Juvenile leaves 0.5\u20131 cm wide; fruit 3\u20134 mm diam.","item":"63639"},{"parent_id":"983363","lead_id":"983366","lead_text":"Juvenile leaves 0.6\u20131.5 cm wide; fruit 4\u20137 mm diam.","item":"63637"},{"parent_id":"983368","lead_id":"983369","lead_text":"Box bark persistent to at least mid-stem; juvenile leaves 0.4\u20131 cm wide","item":"63638"},{"parent_id":"983368","lead_id":"983371","lead_text":"Box bark forming a short basal stocking; juvenile leaves 1\u20131.8 cm wide","item":null},{"parent_id":"983371","lead_id":"983372","lead_text":"Adult leaves held erect, 6\u201310 cm long, 0.7\u20131.6 cm wide","item":"63637"},{"parent_id":"983371","lead_id":"983374","lead_text":"Adult leaves pendulous, 7\u201312 cm long, 1\u20132 cm wide","item":"63641"}]}